.coveragerc
.gitignore
LICENSE
Makefile
README.md
setup.cfg
setup.py
tox.ini
python_swagger_ui.egg-info/PKG-INFO
python_swagger_ui.egg-info/SOURCES.txt
python_swagger_ui.egg-info/dependency_links.txt
python_swagger_ui.egg-info/requires.txt
python_swagger_ui.egg-info/top_level.txt
swagger/__init__.py
swagger/_version.py
swagger/ui.py
swagger/static/index.html
swagger/static/o2c.html
swagger/static/swagger-ui.js
swagger/static/swagger-ui.min.js
swagger/static/css/print.css
swagger/static/css/reset.css
swagger/static/css/screen.css
swagger/static/css/style.css
swagger/static/css/typography.css
swagger/static/fonts/DroidSans-Bold.ttf
swagger/static/fonts/DroidSans.ttf
swagger/static/images/collapse.gif
swagger/static/images/expand.gif
swagger/static/images/explorer_icons.png
swagger/static/images/favicon-16x16.png
swagger/static/images/favicon-32x32.png
swagger/static/images/favicon.ico
swagger/static/images/logo_small.png
swagger/static/images/pet_store_api.png
swagger/static/images/throbber.gif
swagger/static/images/wordnik_api.png
swagger/static/lang/en.js
swagger/static/lang/translator.js
swagger/static/lib/backbone-min.js
swagger/static/lib/handlebars-2.0.0.js
swagger/static/lib/highlight.9.1.0.pack.js
swagger/static/lib/highlight.9.1.0.pack_extended.js
swagger/static/lib/jquery-1.8.0.min.js
swagger/static/lib/jquery.ba-bbq.min.js
swagger/static/lib/jquery.slideto.min.js
swagger/static/lib/jquery.wiggle.min.js
swagger/static/lib/js-yaml.min.js
swagger/static/lib/jsoneditor.min.js
swagger/static/lib/lodash.min.js
swagger/static/lib/marked.js
swagger/static/lib/swagger-oauth.js
tests/test_foo.py