Metadata-Version: 1.1
Name: python-swagger-ui
Version: 0.1
Summary: Swagger UI displaying swagger YAML definition
Home-page: https://github.com/growbots/python_swagger_ui/
Author: Growbots
Author-email: lukasz.jakobiec@growbots.com
License: UNKNOWN
Platform: UNKNOWN
Classifier: Operating System :: OS Independent
Classifier: Intended Audience :: Developers
Classifier: Programming Language :: Python
Classifier: Programming Language :: Python :: 2
Classifier: Programming Language :: Python :: 2.7
Classifier: Programming Language :: Python :: 3
Classifier: Programming Language :: Python :: 3.4
Classifier: Programming Language :: Python :: 3.5
